usb_inspector/__init__.py
usb_inspector/cli.py
usb_inspector/db.py
usb_inspector/example.py
usb_inspector/monitor.py
usb_inspector/update.py
usb_inspector/data/usb.ids
usb_inspector-0.2.2.dist-info/licenses/AUTHORS.md
usb_inspector-0.2.2.dist-info/licenses/LICENSE
usb_inspector-0.2.2.dist-info/METADATA
usb_inspector-0.2.2.dist-info/WHEEL
usb_inspector-0.2.2.dist-info/entry_points.txt
usb_inspector-0.2.2.dist-info/top_level.txt
usb_inspector-0.2.2.dist-info/RECORD
