Metadata-Version: 2.4
Name: usb-inspector
Version: 0.2.2
Summary: A cross-platform tool to monitor and inspect USB devices connected to the host system.
Author-email: Tim Santor <tsantor@xstudios.com>
Project-URL: Repository, https://bitbucket.org/xstudios/usb-inspector.git
Project-URL: Issues, https://bitbucket.org/xstudios/usb-inspector/issues
Project-URL: Changelog, https://bitbucket.org/xstudios/usb-inspector/blob/master/HISTORY.md
Classifier: Development Status :: 5 - Production/Stable
Classifier: Environment :: Console
Classifier: Intended Audience :: Developers
Classifier: Natural Language :: English
Classifier: Programming Language :: Python :: 3.11
Classifier: Programming Language :: Python :: 3.12
Classifier: Programming Language :: Python :: 3.13
Classifier: Programming Language :: Python :: 3.14
Requires-Python: >=3.11
License-File: LICENSE
License-File: AUTHORS.md
Requires-Dist: chardet>=5.2.0
Requires-Dist: click>=8.3.0
Requires-Dist: numpy==2.3.3
Requires-Dist: pandas==2.3.3
Requires-Dist: platformdirs>=4.5.0
Requires-Dist: pyusb>=1.3.1
Requires-Dist: requests>=2.32.5
Requires-Dist: tabulate>=0.9.0
Dynamic: license-file
